MANIFEST.in
README.rst
setup.py
butterknife/__init__.py
butterknife/api.py
butterknife/cli.py
butterknife/fssum.py
butterknife/pool.py
butterknife/subvol.py
butterknife/update.py
butterknife/verify.py
butterknife.egg-info/PKG-INFO
butterknife.egg-info/SOURCES.txt
butterknife.egg-info/dependency_links.txt
butterknife.egg-info/pbr.json
butterknife.egg-info/requires.txt
butterknife.egg-info/top_level.txt
butterknife/templates/index.html
butterknife/templates/packages.html
butterknife/transport/__init__.py
butterknife/transport/http.py
butterknife/transport/ssh.py
misc/butterknife