Metadata-Version: 1.1
Name: butterknife
Version: 0.1.16
Summary: Butterknife makes bare-metal Linux deployment dead-simple using the Linux Containers (LXC) and Btrfs filesystem.
Home-page: http://github.com/laurivosandi/butterknife
Author: Lauri Võsandi
Author-email: lauri.vosandi@gmail.com
License: MIT
Keywords: btrfs falcon multicast http snapshot bare-metal lxc jinja2
Platform: UNKNOWN
Classifier: Development Status :: 4 - Beta
Classifier: Environment :: Console
Classifier: Intended Audience :: Developers
Classifier: Intended Audience :: System Administrators
Classifier: License :: Freely Distributable
Classifier: License :: OSI Approved :: MIT License
Classifier: Natural Language :: English
Classifier: Operating System :: POSIX :: Linux
Classifier: Programming Language :: Python
Classifier: Programming Language :: Python :: 3 :: Only
Classifier: Topic :: System :: Recovery Tools
Classifier: Topic :: System :: Software Distribution
